{    "Changes": [
{	"Action": "EditData",
	"Target": "Data/Characters",
	"Entries": {"Temp": {
					"CanSocialize" : "FALSE",
		"BirthSeason": "Fall",
		"BirthDay": 2,
					"Manner": "Rude",
					"SocialAnxiety": "Shy",
					"Optimism": "Negative",
					"Gender": "Male",
					"CanBeRomanced": false,
					"LoveInterest": "null",
					"HomeRegion": "Town",
					"FriendsAndFamily": {},
		"Home": [{
			"Id": "Default",
			"Location": "Custom_Xiddav_BrickHouseLeft",
			"Tile": {  "X": 19,"Y": 5  },
			"Direction": "1"}],
					"DisplayName": "{{i18n:Temp}}",
			"Age": "Adult"}}},

{"Action": "Load",
      "Target": "Characters/Temp",
      "FromFile": "Temp/Characters.png"},
{"Action": "Load",
      "Target": "Portraits/Temp",
      "FromFile": "Temp/Portrait.png"},

{"Action": "Load",
      "Target": "Characters/schedules/Temp",
      "FromFile": "Temp/schedule.json"},
{"Action": "Load",
      "Target": "Characters/Dialogue/Temp",
      "FromFile": "Temp/Dialogue.json"},

{"Action": "EditData",
"Target": "Characters/Dialogue/Temp",
	"Entries": {    
		"Introduction":"{{i18n:Temp_Introduction}}",
  "Mon": "{{i18n:Temp_Mon}}",
  "Tue": "{{i18n:Temp_Tue}}",
  "Wed": "{{i18n:Temp_Wed}}",
  "Thu": "{{i18n:Temp_Thu}}",
  "Fri": "{{i18n:Temp_Fri}}",
  "Sat": "{{i18n:Temp_Sat}}",
  "Sun": "{{i18n:Temp_Sun}}",
	}},
 ]}